ivrit/__init__.py
ivrit/audio.py
ivrit/diarization.py
ivrit/types.py
ivrit/utils.py
ivrit-0.2.0.dist-info/METADATA
ivrit-0.2.0.dist-info/WHEEL
ivrit-0.2.0.dist-info/RECORD
