Metadata-Version: 2.4
Name: ivrit
Version: 0.2.0
Summary: ivrit.ai helper package
Author-email: Yair Lifshitz <yair@ivrit.ai>, Yoad Snapir <yoad@ivrit.ai>, Yanir Marmor <yanir@ivrit.ai>, Kinneret Misgav <kinneret@ivrit.ai>
License: MIT
Classifier: Development Status :: 3 - Alpha
Classifier: Intended Audience :: Developers
Classifier: License :: OSI Approved :: MIT License
Classifier: Programming Language :: Python :: 3
Classifier: Programming Language :: Python :: 3.9
Classifier: Programming Language :: Python :: 3.10
Classifier: Programming Language :: Python :: 3.11
Classifier: Programming Language :: Python :: 3.12
Classifier: Programming Language :: Python :: 3.13
Requires-Python: >=3.9
Requires-Dist: aiohttp>=3.8.0
Requires-Dist: requests>=2.32.3
Provides-Extra: all
Requires-Dist: faster-whisper>=1.1.1; extra == 'all'
Requires-Dist: numpy>=1.20.0; extra == 'all'
Requires-Dist: pandas>=1.3.0; extra == 'all'
Requires-Dist: pyannote-audio>=3.3.2; extra == 'all'
Requires-Dist: pywhispercpp; extra == 'all'
Requires-Dist: scikit-learn>=1.0.0; extra == 'all'
Requires-Dist: speechbrain>=0.5.0; extra == 'all'
Requires-Dist: stable-ts-whisperless>=2.18.3; extra == 'all'
Requires-Dist: torch; extra == 'all'
Requires-Dist: torchaudio; extra == 'all'
